<?xml version="1.0"?>
<opencv_storage>
<Distance>15</Distance>
<PointsInitAsMatrix type_id="opencv-matrix">
  <rows>2</rows>
  <cols>4</cols>
  <dt>f</dt>
  <data>
    75. 76. 74. 0. 234. 237. 233. 8.96831017e-44</data></PointsInitAsMatrix>
<PointsEndAsMatrix type_id="opencv-matrix">
  <rows>2</rows>
  <cols>4</cols>
  <dt>f</dt>
  <data>
    68. 68. 69. 0. 478. 473. 477. 0.</data></PointsEndAsMatrix>
<LengthAsMatrix type_id="opencv-matrix">
  <rows>1</rows>
  <cols>4</cols>
  <dt>f</dt>
  <data>
    2.44100388e+02 2.36135559e+02 2.44051224e+02 0.</data></LengthAsMatrix>
</opencv_storage>
